Workbook

Sheet Raw Data
A1: 📊 Personal Finance — Raw Transaction Data
A2: Date | B2: Month | C2: Income Source | D2: Expense Category | E2: Expense Type | F2: Payment Mode | G2: Amount | H2: Indicator | I2: Savings | J2: Budget Allocated | K2: Budget Remaining | L2: Notes
A3: 03-01-2026 | B3: Jan | C3: Salary | E3: Variable | F3: UPI | G3: 18982 | H3: Income | J3: 10000 | K3: =IF(H3="Expense",J3-G3,"N/A") -> N/A
A4: 04-01-2026 | B4: Jan | D4: Travel | E4: Variable | F4: Bank | G4: 5977 | H4: Expense | J4: 10000 | K4: =IF(H4="Expense",J4-G4,"N/A") -> 4023
A5: 05-01-2026 | B5: Jan | D5: Food | E5: Variable | F5: Credit Card | G5: 7197 | H5: Expense | J5: 10000 | K5: =IF(H5="Expense",J5-G5,"N/A") -> 2803
A6: 06-01-2026 | B6: Jan | C6: Business | E6: Variable | F6: Cash | G6: 7664 | H6: Income | J6: 10000 | K6: =IF(H6="Expense",J6-G6,"N/A") -> N/A
A7: 07-01-2026 | B7: Jan | D7: Shopping | E7: Variable | F7: Cash | G7: 7798 | H7: Expense | J7: 10000 | K7: =IF(H7="Expense",J7-G7,"N/A") -> 2202
A8: 08-01-2026 | B8: Jan | D8: Travel | E8: Variable | F8: Credit Card | G8: 3186 | H8: Expense | J8: 10000 | K8: =IF(H8="Expense",J8-G8,"N/A") -> 6814
A9: 09-01-2026 | B9: Jan | C9: Business | E9: Variable | F9: Credit Card | G9: 23666 | H9: Income | J9: 10000 | K9: =IF(H9="Expense",J9-G9,"N/A") -> N/A
A10: 10-01-2026 | B10: Jan | C10: Business | E10: Variable | F10: Cash | G10: 23532 | H10: Income | J10: 10000 | K10: =IF(H10="Expense",J10-G10,"N/A") -> N/A
A11: 11-01-2026 | B11: Jan | D11: Shopping | E11: Variable | F11: Bank | G11: 2329 | H11: Expense | J11: 10000 | K11: =IF(H11="Expense",J11-G11,"N/A") -> 7671
A12: 12-01-2026 | B12: Jan | C12: Salary | E12: Variable | F12: Cash | G12: 7171 | H12: Income | J12: 10000 | K12: =IF(H12="Expense",J12-G12,"N/A") -> N/A
A13: 13-01-2026 | B13: Jan | C13: Salary | E13: Variable | F13: Bank | G13: 11356 | H13: Income | J13: 10000 | K13: =IF(H13="Expense",J13-G13,"N/A") -> N/A
A14: 14-01-2026 | B14: Jan | C14: Freelance | E14: Variable | F14: Cash | G14: 14668 | H14: Income | J14: 10000 | K14: =IF(H14="Expense",J14-G14,"N/A") -> N/A
A15: 15-01-2026 | B15: Jan | D15: EMI | E15: Variable | F15: Bank | G15: 3070 | H15: Expense | J15: 10000 | K15: =IF(H15="Expense",J15-G15,"N/A") -> 6930
A16: 16-01-2026 | B16: Jan | D16: Bills | E16: Variable | F16: UPI | G16: 1086 | H16: Expense | J16: 10000 | K16: =IF(H16="Expense",J16-G16,"N/A") -> 8914
A17: 17-01-2026 | B17: Jan | C17: Business | E17: Variable | F17: Credit Card | G17: 9129 | H17: Income | J17: 10000 | K17: =IF(H17="Expense",J17-G17,"N/A") -> N/A
A18: 18-01-2026 | B18: Jan | D18: Bills | E18: Variable | F18: UPI | G18: 3572 | H18: Expense | J18: 10000 | K18: =IF(H18="Expense",J18-G18,"N/A") -> 6428
A19: 19-01-2026 | B19: Jan | D19: Rent | E19: Fixed | F19: UPI | G19: 3430 | H19: Expense | J19: 10000 | K19: =IF(H19="Expense",J19-G19,"N/A") -> 6570
A20: 20-01-2026 | B20: Jan | D20: Rent | E20: Fixed | F20: Cash | G20: 6284 | H20: Expense | J20: 10000 | K20: =IF(H20="Expense",J20-G20,"N/A") -> 3716
A21: 21-01-2026 | B21: Jan | D21: Travel | E21: Variable | F21: Credit Card | G21: 4494 | H21: Expense | J21: 10000 | K21: =IF(H21="Expense",J21-G21,"N/A") -> 5506
A22: 22-01-2026 | B22: Jan | D22: Travel | E22: Variable | F22: Cash | G22: 4555 | H22: Expense | J22: 10000 | K22: =IF(H22="Expense",J22-G22,"N/A") -> 5445
A23: 23-01-2026 | B23: Jan | D23: Shopping | E23: Variable | F23: Bank | G23: 3025 | H23: Expense | J23: 10000 | K23: =IF(H23="Expense",J23-G23,"N/A") -> 6975
A24: 24-01-2026 | B24: Jan | D24: Food | E24: Variable | F24: Credit Card | G24: 5297 | H24: Expense | J24: 10000 | K24: =IF(H24="Expense",J24-G24,"N/A") -> 4703
A25: 25-01-2026 | B25: Jan | C25: Freelance | E25: Variable | F25: Credit Card | G25: 22310 | H25: Income | J25: 10000 | K25: =IF(H25="Expense",J25-G25,"N/A") -> N/A
A26: 26-01-2026 | B26: Jan | D26: Food | E26: Variable | F26: Cash | G26: 8876 | H26: Expense | J26: 10000 | K26: =IF(H26="Expense",J26-G26,"N/A") -> 1124
A27: 27-01-2026 | B27: Jan | C27: Business | E27: Variable | F27: Bank | G27: 23790 | H27: Income | J27: 10000 | K27: =IF(H27="Expense",J27-G27,"N/A") -> N/A
A28: 28-01-2026 | B28: Jan | D28: Rent | E28: Fixed | F28: Bank | G28: 4667 | H28: Expense | J28: 10000 | K28: =IF(H28="Expense",J28-G28,"N/A") -> 5333
A29: 29-01-2026 | B29: Jan | C29: Salary | E29: Variable | F29: Credit Card | G29: 26898 | H29: Income | J29: 10000 | K29: =IF(H29="Expense",J29-G29,"N/A") -> N/A
A30: 30-01-2026 | B30: Jan | C30: Salary | E30: Variable | F30: Cash | G30: 17086 | H30: Income | J30: 10000 | K30: =IF(H30="Expense",J30-G30,"N/A") -> N/A
A31: 31-01-2026 | B31: Jan | D31: Food | E31: Variable | F31: Cash | G31: 4431 | H31: Expense | J31: 10000 | K31: =IF(H31="Expense",J31-G31,"N/A") -> 5569
A32: 01-02-2026 | B32: Feb | C32: Salary | E32: Variable | F32: Cash | G32: 10480 | H32: Income | J32: 10000 | K32: =IF(H32="Expense",J32-G32,"N/A") -> N/A
A33: 02-02-2026 | B33: Feb | C33: Business | E33: Variable | F33: Credit Card | G33: 28674 | H33: Income | J33: 10000 | K33: =IF(H33="Expense",J33-G33,"N/A") -> N/A
A34: 03-02-2026 | B34: Feb | C34: Freelance | E34: Variable | F34: Cash | G34: 20894 | H34: Income | J34: 10000 | K34: =IF(H34="Expense",J34-G34,"N/A") -> N/A
A35: 04-02-2026 | B35: Feb | C35: Business | E35: Variable | F35: Bank | G35: 25982 | H35: Income | J35: 10000 | K35: =IF(H35="Expense",J35-G35,"N/A") -> N/A
A36: 05-02-2026 | B36: Feb | C36: Business | E36: Variable | F36: Cash | G36: 6102 | H36: Income | J36: 10000 | K36: =IF(H36="Expense",J36-G36,"N/A") -> N/A
A37: 06-02-2026 | B37: Feb | D37: Rent | E37: Fixed | F37: Credit Card | G37: 4276 | H37: Expense | J37: 10000 | K37: =IF(H37="Expense",J37-G37,"N/A") -> 5724
A38: 07-02-2026 | B38: Feb | C38: Salary | E38: Variable | F38: Cash | G38: 15498 | H38: Income | J38: 10000 | K38: =IF(H38="Expense",J38-G38,"N/A") -> N/A
A39: 08-02-2026 | B39: Feb | D39: Rent | E39: Fixed | F39: Credit Card | G39: 3030 | H39: Expense | J39: 10000 | K39: =IF(H39="Expense",J39-G39,"N/A") -> 6970
A40: 09-02-2026 | B40: Feb | C40: Business | E40: Variable | F40: UPI | G40: 15122 | H40: Income | J40: 10000 | K40: =IF(H40="Expense",J40-G40,"N/A") -> N/A
A41: 10-02-2026 | B41: Feb | D41: Food | E41: Variable | F41: Bank | G41: 6512 | H41: Expense | J41: 10000 | K41: =IF(H41="Expense",J41-G41,"N/A") -> 3488
A42: 11-02-2026 | B42: Feb | D42: Shopping | E42: Variable | F42: Bank | G42: 4508 | H42: Expense | J42: 10000 | K42: =IF(H42="Expense",J42-G42,"N/A") -> 5492
A43: 12-02-2026 | B43: Feb | D43: Rent | E43: Fixed | F43: Credit Card | G43: 8309 | H43: Expense | J43: 10000 | K43: =IF(H43="Expense",J43-G43,"N/A") -> 1691
A44: 13-02-2026 | B44: Feb | C44: Freelance | E44: Variable | F44: UPI | G44: 28991 | H44: Income | J44: 10000 | K44: =IF(H44="Expense",J44-G44,"N/A") -> N/A
A45: 14-02-2026 | B45: Feb | D45: EMI | E45: Variable | F45: UPI | G45: 8201 | H45: Expense | J45: 10000 | K45: =IF(H45="Expense",J45-G45,"N/A") -> 1799
A46: 15-02-2026 | B46: Feb | C46: Salary | E46: Variable | F46: Cash | G46: 18425 | H46: Income | J46: 10000 | K46: =IF(H46="Expense",J46-G46,"N/A") -> N/A
A47: 16-02-2026 | B47: Feb | C47: Business | E47: Variable | F47: Credit Card | G47: 24396 | H47: Income | J47: 10000 | K47: =IF(H47="Expense",J47-G47,"N/A") -> N/A
A48: 17-02-2026 | B48: Feb | D48: Food | E48: Variable | F48: UPI | G48: 5716 | H48: Expense | J48: 10000 | K48: =IF(H48="Expense",J48-G48,"N/A") -> 4284
A49: 18-02-2026 | B49: Feb | D49: Travel | E49: Variable | F49: Cash | G49: 5125 | H49: Expense | J49: 10000 | K49: =IF(H49="Expense",J49-G49,"N/A") -> 4875
A50: 19-02-2026 | B50: Feb | C50: Business | E50: Variable | F50: Credit Card | G50: 16433 | H50: Income | J50: 10000 | K50: =IF(H50="Expense",J50-G50,"N/A") -> N/A
A51: 20-02-2026 | B51: Feb | D51: Bills | E51: Variable | F51: Cash | G51: 6952 | H51: Expense | J51: 10000 | K51: =IF(H51="Expense",J51-G51,"N/A") -> 3048
A52: 21-02-2026 | B52: Feb | C52: Freelance | E52: Variable | F52: Bank | G52: 27449 | H52: Income | J52: 10000 | K52: =IF(H52="Expense",J52-G52,"N/A") -> N/A
A53: 22-02-2026 | B53: Feb | C53: Salary | E53: Variable | F53: Bank | G53: 6112 | H53: Income | J53: 10000 | K53: =IF(H53="Expense",J53-G53,"N/A") -> N/A
A54: 23-02-2026 | B54: Feb | D54: EMI | E54: Variable | F54: UPI | G54: 229 | H54: Expense | J54: 10000 | K54: =IF(H54="Expense",J54-G54,"N/A") -> 9771
A55: 24-02-2026 | B55: Feb | C55: Business | E55: Variable | F55: Bank | G55: 16254 | H55: Income | J55: 10000 | K55: =IF(H55="Expense",J55-G55,"N/A") -> N/A
A56: 25-02-2026 | B56: Feb | C56: Freelance | E56: Variable | F56: Credit Card | G56: 6721 | H56: Income | J56: 10000 | K56: =IF(H56="Expense",J56-G56,"N/A") -> N/A
A57: 26-02-2026 | B57: Feb | C57: Salary | E57: Variable | F57: Credit Card | G57: 19611 | H57: Income | J57: 10000 | K57: =IF(H57="Expense",J57-G57,"N/A") -> N/A
A58: 27-02-2026 | B58: Feb | D58: Travel | E58: Variable | F58: Bank | G58: 2792 | H58: Expense | J58: 10000 | K58: =IF(H58="Expense",J58-G58,"N/A") -> 7208
A59: 28-02-2026 | B59: Feb | C59: Freelance | E59: Variable | F59: Credit Card | G59: 23596 | H59: Income | J59: 10000 | K59: =IF(H59="Expense",J59-G59,"N/A") -> N/A
A60: 01-03-2026 | B60: Mar | C60: Business | E60: Variable | F60: Bank | G60: 9581 | H60: Income | J60: 10000 | K60: =IF(H60="Expense",J60-G60,"N/A") -> N/A
A61: 02-03-2026 | B61: Mar | D61: Rent | E61: Fixed | F61: Bank | G61: 9820 | H61: Expense | J61: 10000 | K61: =IF(H61="Expense",J61-G61,"N/A") -> 180
A62: 03-03-2026 | B62: Mar | D62: Shopping | E62: Variable | F62: Cash | G62: 3292 | H62: Expense | J62: 10000 | K62: =IF(H62="Expense",J62-G62,"N/A") -> 6708
A63: 04-03-2026 | B63: Mar | D63: Travel | E63: Variable | F63: Credit Card | G63: 5765 | H63: Expense | J63: 10000 | K63: =IF(H63="Expense",J63-G63,"N/A") -> 4235
A64: 05-03-2026 | B64: Mar | D64: Food | E64: Variable | F64: UPI | G64: 1345 | H64: Expense | J64: 10000 | K64: =IF(H64="Expense",J64-G64,"N/A") -> 8655
A65: 06-03-2026 | B65: Mar | D65: Travel | E65: Variable | F65: Cash | G65: 1765 | H65: Expense | J65: 10000 | K65: =IF(H65="Expense",J65-G65,"N/A") -> 8235
A66: 07-03-2026 | B66: Mar | D66: EMI | E66: Variable | F66: Credit Card | G66: 7069 | H66: Expense | J66: 10000 | K66: =IF(H66="Expense",J66-G66,"N/A") -> 2931
A67: 08-03-2026 | B67: Mar | D67: Rent | E67: Fixed | F67: Cash | G67: 1476 | H67: Expense | J67: 10000 | K67: =IF(H67="Expense",J67-G67,"N/A") -> 8524
A68: 09-03-2026 | B68: Mar | C68: Freelance | E68: Variable | F68: Credit Card | G68: 9606 | H68: Income | J68: 10000 | K68: =IF(H68="Expense",J68-G68,"N/A") -> N/A
A69: 10-03-2026 | B69: Mar | C69: Salary | E69: Variable | F69: UPI | G69: 29070 | H69: Income | J69: 10000 | K69: =IF(H69="Expense",J69-G69,"N/A") -> N/A
A70: 11-03-2026 | B70: Mar | C70: Freelance | E70: Variable | F70: Credit Card | G70: 24038 | H70: Income | J70: 10000 | K70: =IF(H70="Expense",J70-G70,"N/A") -> N/A
A71: 12-03-2026 | B71: Mar | D71: EMI | E71: Variable | F71: Cash | G71: 3532 | H71: Expense | J71: 10000 | K71: =IF(H71="Expense",J71-G71,"N/A") -> 6468
A72: 13-03-2026 | B72: Mar | D72: Shopping | E72: Variable | F72: UPI | G72: 8504 | H72: Expense | J72: 10000 | K72: =IF(H72="Expense",J72-G72,"N/A") -> 1496
A73: 14-03-2026 | B73: Mar | C73: Salary | E73: Variable | F73: Cash | G73: 28769 | H73: Income | J73: 10000 | K73: =IF(H73="Expense",J73-G73,"N/A") -> N/A
A74: 15-03-2026 | B74: Mar | C74: Freelance | E74: Variable | F74: Cash | G74: 19246 | H74: Income | J74: 10000 | K74: =IF(H74="Expense",J74-G74,"N/A") -> N/A
A75: 16-03-2026 | B75: Mar | D75: EMI | E75: Variable | F75: Cash | G75: 6072 | H75: Expense | J75: 10000 | K75: =IF(H75="Expense",J75-G75,"N/A") -> 3928
A76: 17-03-2026 | B76: Mar | D76: EMI | E76: Variable | F76: Credit Card | G76: 7095 | H76: Expense | J76: 10000 | K76: =IF(H76="Expense",J76-G76,"N/A") -> 2905
A77: 18-03-2026 | B77: Mar | C77: Business | E77: Variable | F77: Credit Card | G77: 18135 | H77: Income | J77: 10000 | K77: =IF(H77="Expense",J77-G77,"N/A") -> N/A
A78: 19-03-2026 | B78: Mar | D78: Food | E78: Variable | F78: Cash | G78: 6892 | H78: Expense | J78: 10000 | K78: =IF(H78="Expense",J78-G78,"N/A") -> 3108
A79: 20-03-2026 | B79: Mar | D79: Shopping | E79: Variable | F79: Bank | G79: 7356 | H79: Expense | J79: 10000 | K79: =IF(H79="Expense",J79-G79,"N/A") -> 2644
A80: 21-03-2026 | B80: Mar | D80: EMI | E80: Variable | F80: Credit Card | G80: 7791 | H80: Expense | J80: 10000 | K80: =IF(H80="Expense",J80-G80,"N/A") -> 2209
A81: 22-03-2026 | B81: Mar | C81: Business | E81: Variable | F81: Credit Card | G81: 13460 | H81: Income | J81: 10000 | K81: =IF(H81="Expense",J81-G81,"N/A") -> N/A
A82: 23-03-2026 | B82: Mar | C82: Freelance | E82: Variable | F82: Credit Card | G82: 10573 | H82: Income | J82: 10000 | K82: =IF(H82="Expense",J82-G82,"N/A") -> N/A
A83: 24-03-2026 | B83: Mar | D83: Bills | E83: Variable | F83: Credit Card | G83: 9762 | H83: Expense | J83: 10000 | K83: =IF(H83="Expense",J83-G83,"N/A") -> 238
A84: 25-03-2026 | B84: Mar | D84: Travel | E84: Variable | F84: UPI | G84: 5478 | H84: Expense | J84: 10000 | K84: =IF(H84="Expense",J84-G84,"N/A") -> 4522
A85: 26-03-2026 | B85: Mar | D85: Shopping | E85: Variable | F85: Bank | G85: 8115 | H85: Expense | J85: 10000 | K85: =IF(H85="Expense",J85-G85,"N/A") -> 1885
A86: 27-03-2026 | B86: Mar | C86: Business | E86: Variable | F86: UPI | G86: 10836 | H86: Income | J86: 10000 | K86: =IF(H86="Expense",J86-G86,"N/A") -> N/A
A87: 28-03-2026 | B87: Mar | C87: Salary | E87: Variable | F87: Bank | G87: 24299 | H87: Income | J87: 10000 | K87: =IF(H87="Expense",J87-G87,"N/A") -> N/A
A88: 29-03-2026 | B88: Mar | D88: Bills | E88: Variable | F88: Bank | G88: 1680 | H88: Expense | J88: 10000 | K88: =IF(H88="Expense",J88-G88,"N/A") -> 8320
A89: 30-03-2026 | B89: Mar | D89: Travel | E89: Variable | F89: Credit Card | G89: 8331 | H89: Expense | J89: 10000 | K89: =IF(H89="Expense",J89-G89,"N/A") -> 1669
A90: 31-03-2026 | B90: Mar | C90: Salary | E90: Variable | F90: UPI | G90: 27597 | H90: Income | J90: 10000 | K90: =IF(H90="Expense",J90-G90,"N/A") -> N/A
A91: 01-04-2026 | B91: Apr | D91: Shopping | E91: Variable | F91: Bank | G91: 2115 | H91: Expense | J91: 10000 | K91: =IF(H91="Expense",J91-G91,"N/A") -> 7885
A92: 02-04-2026 | B92: Apr | D92: Bills | E92: Variable | F92: Credit Card | G92: 7783 | H92: Expense | J92: 10000 | K92: =IF(H92="Expense",J92-G92,"N/A") -> 2217
A93: 03-04-2026 | B93: Apr | D93: Bills | E93: Variable | F93: Cash | G93: 4328 | H93: Expense | J93: 10000 | K93: =IF(H93="Expense",J93-G93,"N/A") -> 5672
A94: 04-04-2026 | B94: Apr | C94: Freelance | E94: Variable | F94: UPI | G94: 24792 | H94: Income | J94: 10000 | K94: =IF(H94="Expense",J94-G94,"N/A") -> N/A
A95: 05-04-2026 | B95: Apr | C95: Salary | E95: Variable | F95: Bank | G95: 29232 | H95: Income | J95: 10000 | K95: =IF(H95="Expense",J95-G95,"N/A") -> N/A
A96: 06-04-2026 | B96: Apr | C96: Freelance | E96: Variable | F96: Credit Card | G96: 18107 | H96: Income | J96: 10000 | K96: =IF(H96="Expense",J96-G96,"N/A") -> N/A
A97: 07-04-2026 | B97: Apr | C97: Salary | E97: Variable | F97: Cash | G97: 12089 | H97: Income | J97: 10000 | K97: =IF(H97="Expense",J97-G97,"N/A") -> N/A
A98: 08-04-2026 | B98: Apr | D98: Travel | E98: Variable | F98: Credit Card | G98: 706 | H98: Expense | J98: 10000 | K98: =IF(H98="Expense",J98-G98,"N/A") -> 9294
A99: 09-04-2026 | B99: Apr | C99: Business | E99: Variable | F99: Credit Card | G99: 15432 | H99: Income | J99: 10000 | K99: =IF(H99="Expense",J99-G99,"N/A") -> N/A
A100: 10-04-2026 | B100: Apr | C100: Salary | E100: Variable | F100: Cash | G100: 15278 | H100: Income | J100: 10000 | K100: =IF(H100="Expense",J100-G100,"N/A") -> N/A
...

Sheet Cleaned Data

Sheet Budget Planning
A1: 🎯 Budget Planning & Tracking
A2: Category | B2: Monthly Budget | C2: Actual Spend | D2: Variance | E2: Status
A3: Food | B3: 10000 | C3: =SUMIFS('Raw Data'!G:G,'Raw Data'!D:D,"Food") -> 46266 | D3: =B3-C3 -> -36266 | E3: =IF(D3>=0,"✅ Under Budget","⚠️ Over Budget") -> ⚠️ Over Budget
A4: Rent | B4: 10000 | C4: =SUMIFS('Raw Data'!G:G,'Raw Data'!D:D,"Rent") -> 49757 | D4: =B4-C4 -> -39757 | E4: =IF(D4>=0,"✅ Under Budget","⚠️ Over Budget") -> ⚠️ Over Budget
A5: Travel | B5: 10000 | C5: =SUMIFS('Raw Data'!G:G,'Raw Data'!D:D,"Travel") -> 48174 | D5: =B5-C5 -> -38174 | E5: =IF(D5>=0,"✅ Under Budget","⚠️ Over Budget") -> ⚠️ Over Budget
A6: Shopping | B6: 10000 | C6: =SUMIFS('Raw Data'!G:G,'Raw Data'!D:D,"Shopping") -> 47042 | D6: =B6-C6 -> -37042 | E6: =IF(D6>=0,"✅ Under Budget","⚠️ Over Budget") -> ⚠️ Over Budget
A7: EMI | B7: 10000 | C7: =SUMIFS('Raw Data'!G:G,'Raw Data'!D:D,"EMI") -> 43059 | D7: =B7-C7 -> -33059 | E7: =IF(D7>=0,"✅ Under Budget","⚠️ Over Budget") -> ⚠️ Over Budget
A8: Bills | B8: 10000 | C8: =SUMIFS('Raw Data'!G:G,'Raw Data'!D:D,"Bills") -> 35163 | D8: =B8-C8 -> -25163 | E8: =IF(D8>=0,"✅ Under Budget","⚠️ Over Budget") -> ⚠️ Over Budget
A9: TOTAL | B9: =SUM(B3:B8) -> 60000 | C9: =SUM(C3:C8) -> 269461 | D9: =SUM(D3:D8) -> -209461 | E9: =IF(D9>=0,"✅ Under Budget","⚠️ Over Budget") -> ⚠️ Over Budget

Sheet KPI Summary
A1: 💰 KPI Summary Dashboard
A2: Key Performance Indicators — Personal Finance FY 2026
A4: 💵 Total Income
A5: =SUMIFS('Raw Data'!G:G,'Raw Data'!H:H,"Income") -> 876368 | C5: 💸 Total Expense
C6: =SUMIFS('Raw Data'!G:G,'Raw Data'!H:H,"Expense") -> 269461 | E6: 📈 Net Savings
A7: 💹 Savings Rate | C7: 📅 Avg Monthly Savings | E7: 🏦 Total Transactions
A8: =IFERROR(B5/B4,0) -> 0 | C8: =IFERROR(B6/4,0) -> 0 | E8: =COUNTA('Raw Data'!H3:H102)-COUNTBLANK('Raw Data'!H3:H102) -> 100

Sheet Dashboard
A1: 💼 PERSONAL FINANCE DASHBOARD | FY 2026
A2: Powered by Real Transaction Data • Jan – Apr 2026 • All amounts in INR (₹)
A4: 💵 TOTAL INCOME | D4: 💸 TOTAL EXPENSE | G4: 📈 NET SAVINGS | J4: 💹 SAVINGS RATE | M4: 🏦 TRANSACTIONS
A5: ='KPI Summary'!B5 -> 0 | D5: ='KPI Summary'!D5 -> 0 | G5: ='KPI Summary'!F5 -> 0 | J5: ='KPI Summary'!B8 -> 0 | M5: ='KPI Summary'!F8 -> 0
A10: 📅 MONTHLY BREAKDOWN | I10: 📊 EXPENSE BY CATEGORY
A11: Month | B11: Income (₹) | C11: Expense (₹) | D11: Net Savings (₹) | E11: Savings Rate | F11: vs Prev Month | I11: Category | J11: Amount (₹) | K11: % Share | L11: Budget (₹) | M11: Variance (₹) | N11: Status
A12: Jan | B12: ='Monthly Analysis'!B3 -> 206252 | C12: ='Monthly Analysis'!C3 -> 79274 | D12: ='Monthly Analysis'!D3 -> 126978 | E12: ='Monthly Analysis'!E3 -> 0.61564494 | F12: =IF(12>12,D12-D11,"--") -> -- | I12: Food | J12: ='Monthly Analysis'!H3 -> 46266 | K12: ='Monthly Analysis'!I3 -> 0.17169832 | L12: ='Budget Planning'!B3 -> 10000 | M12: ='Budget Planning'!D3 -> -36266 | N12: =IF(M12>=0,"✅ OK","⚠️ Over") -> ⚠️ Over
A13: Feb | B13: ='Monthly Analysis'!B4 -> 310740 | C13: ='Monthly Analysis'!C4 -> 55650 | D13: ='Monthly Analysis'!D4 -> 255090 | E13: ='Monthly Analysis'!E4 -> 0.82091137 | F13: =IF(13>12,D13-D12,"--") -> 128112 | I13: Rent | J13: ='Monthly Analysis'!H4 -> 48174 | K13: ='Monthly Analysis'!I4 -> 0.17877912 | L13: ='Budget Planning'!B4 -> 10000 | M13: ='Budget Planning'!D4 -> -39757 | N13: =IF(M13>=0,"✅ OK","⚠️ Over") -> ⚠️ Over
A14: Mar | B14: ='Monthly Analysis'!B5 -> 225210 | C14: ='Monthly Analysis'!C5 -> 111140 | D14: ='Monthly Analysis'!D5 -> 114070 | E14: ='Monthly Analysis'!E5 -> 0.50650504 | F14: =IF(14>12,D14-D13,"--") -> -141020 | I14: Travel | J14: ='Monthly Analysis'!H5 -> 47042 | K14: ='Monthly Analysis'!I5 -> 0.17457814 | L14: ='Budget Planning'!B5 -> 10000 | M14: ='Budget Planning'!D5 -> -38174 | N14: =IF(M14>=0,"✅ OK","⚠️ Over") -> ⚠️ Over
A15: Apr | B15: ='Monthly Analysis'!B6 -> 134166 | C15: ='Monthly Analysis'!C6 -> 23397 | D15: ='Monthly Analysis'!D6 -> 110769 | E15: ='Monthly Analysis'!E6 -> 0.82561156 | F15: =IF(15>12,D15-D14,"--") -> -3301 | I15: Shopping | J15: ='Monthly Analysis'!H6 -> 49757 | K15: ='Monthly Analysis'!I6 -> 0.18465381 | L15: ='Budget Planning'!B6 -> 10000 | M15: ='Budget Planning'!D6 -> -37042 | N15: =IF(M15>=0,"✅ OK","⚠️ Over") -> ⚠️ Over
A16: TOTAL | B16: =SUM(B12:B15) -> 876368 | C16: =SUM(C12:C15) -> 269461 | D16: =SUM(D12:D15) -> 606907 | E16: =IFERROR(D16/B16,0) -> 0.69252529 | F16: — | I16: EMI | J16: ='Monthly Analysis'!H7 -> 43059 | K16: ='Monthly Analysis'!I7 -> 0.15979678 | L16: ='Budget Planning'!B7 -> 10000 | M16: ='Budget Planning'!D7 -> -33059 | N16: =IF(M16>=0,"✅ OK","⚠️ Over") -> ⚠️ Over
I17: Bills | J17: ='Monthly Analysis'!H8 -> 35163 | K17: ='Monthly Analysis'!I8 -> 0.13049384 | L17: ='Budget Planning'!B8 -> 10000 | M17: ='Budget Planning'!D8 -> -25163 | N17: =IF(M17>=0,"✅ OK","⚠️ Over") -> ⚠️ Over
I18: TOTAL | J18: =SUM(J12:J17) -> 269461 | K18: 100.0% | L18: ='Budget Planning'!B9 -> 60000 | M18: =IFERROR(L18-J18,0) -> -209461
A20: 🧠 KEY INSIGHTS & ANALYSIS
A21: 💡 Highest Expense | C21: Rent is the largest single expense category, accounting for ~18% of total spend.
A22: 📉 March Alert | C22: March had the highest expenses (₹1,11,140). Monitor recurring costs that month.
A23: 🏆 Best Month | C23: April had the best savings performance with the lowest expense-to-income ratio.
A24: 💰 Income Mix | C24: Income is well-diversified: Salary (37%), Business (36%), Freelance (27%).
A25: 🎯 Savings Target | C25: Current savings rate exceeds 69% — significantly above the recommended 20% benchmark.
A26: ⚠️ Action Item | C26: Shopping and Travel expenses combined equal ~35% of total spend. Review discretionary spend.

Sheet Monthly Analysis
A1: 📅 Monthly Income vs Expense Analysis
A2: Month | B2: Total Income | C2: Total Expense | D2: Net Savings | E2: Savings Rate | G2: Expense Category | H2: Total Amount | I2: % of Expenses | K2: Income Source | L2: Total Amount
A3: Jan | B3: =SUMIFS('Raw Data'!G:G,'Raw Data'!B:B,"Jan",'Raw Data'!H:H,"Income") -> 206252 | C3: =SUMIFS('Raw Data'!G:G,'Raw Data'!B:B,"Jan",'Raw Data'!H:H,"Expense") -> 79274 | D3: =B3-C3 -> 126978 | E3: =IFERROR(D3/B3,0) -> 0.61564494 | G3: Food | H3: =SUMIFS('Raw Data'!G:G,'Raw Data'!D:D,"Food") -> 46266 | I3: =IFERROR(H3/SUM(H3:H8),0) -> 0.17169832 | K3: Salary | L3: =SUMIFS('Raw Data'!G:G,'Raw Data'!C:C,"Salary") -> 317953
A4: Feb | B4: =SUMIFS('Raw Data'!G:G,'Raw Data'!B:B,"Feb",'Raw Data'!H:H,"Income") -> 310740 | C4: =SUMIFS('Raw Data'!G:G,'Raw Data'!B:B,"Feb",'Raw Data'!H:H,"Expense") -> 55650 | D4: =B4-C4 -> 255090 | E4: =IFERROR(D4/B4,0) -> 0.82091137 | G4: Travel | H4: =SUMIFS('Raw Data'!G:G,'Raw Data'!D:D,"Travel") -> 48174 | I4: =IFERROR(H4/SUM(H3:H8),0) -> 0.17877912 | K4: Business | L4: =SUMIFS('Raw Data'!G:G,'Raw Data'!C:C,"Business") -> 307424
A5: Mar | B5: =SUMIFS('Raw Data'!G:G,'Raw Data'!B:B,"Mar",'Raw Data'!H:H,"Income") -> 225210 | C5: =SUMIFS('Raw Data'!G:G,'Raw Data'!B:B,"Mar",'Raw Data'!H:H,"Expense") -> 111140 | D5: =B5-C5 -> 114070 | E5: =IFERROR(D5/B5,0) -> 0.50650504 | G5: Shopping | H5: =SUMIFS('Raw Data'!G:G,'Raw Data'!D:D,"Shopping") -> 47042 | I5: =IFERROR(H5/SUM(H3:H8),0) -> 0.17457814 | K5: Freelance | L5: =SUMIFS('Raw Data'!G:G,'Raw Data'!C:C,"Freelance") -> 250991
A6: Apr | B6: =SUMIFS('Raw Data'!G:G,'Raw Data'!B:B,"Apr",'Raw Data'!H:H,"Income") -> 134166 | C6: =SUMIFS('Raw Data'!G:G,'Raw Data'!B:B,"Apr",'Raw Data'!H:H,"Expense") -> 23397 | D6: =B6-C6 -> 110769 | E6: =IFERROR(D6/B6,0) -> 0.82561156 | G6: Rent | H6: =SUMIFS('Raw Data'!G:G,'Raw Data'!D:D,"Rent") -> 49757 | I6: =IFERROR(H6/SUM(H3:H8),0) -> 0.18465381
G7: EMI | H7: =SUMIFS('Raw Data'!G:G,'Raw Data'!D:D,"EMI") -> 43059 | I7: =IFERROR(H7/SUM(H3:H8),0) -> 0.15979678
G8: Bills | H8: =SUMIFS('Raw Data'!G:G,'Raw Data'!D:D,"Bills") -> 35163 | I8: =IFERROR(H8/SUM(H3:H8),0) -> 0.13049384
